MANIFEST.in
setup.py
netbox_vpn_plugin/__init__.py
netbox_vpn_plugin/filtersets.py
netbox_vpn_plugin/forms.py
netbox_vpn_plugin/models.py
netbox_vpn_plugin/navigation.py
netbox_vpn_plugin/tables.py
netbox_vpn_plugin/urls.py
netbox_vpn_plugin/views.py
netbox_vpn_plugin.egg-info/PKG-INFO
netbox_vpn_plugin.egg-info/SOURCES.txt
netbox_vpn_plugin.egg-info/dependency_links.txt
netbox_vpn_plugin.egg-info/top_level.txt
netbox_vpn_plugin/api/__init__.py
netbox_vpn_plugin/api/serializers.py
netbox_vpn_plugin/api/urls.py
netbox_vpn_plugin/api/views.py
netbox_vpn_plugin/migrations/0001_initial.py
netbox_vpn_plugin/migrations/__init__.py
netbox_vpn_plugin/templates/netbox_vpn_plugin/vpnconnection.html
netbox_vpn_plugin/templates/netbox_vpn_plugin/vpnconnectionphase2.html