Metadata-Version: 2.1
Name: netbox-vpn-plugin
Version: 0.8.2
Summary: Manage VPN Connections in Netbox
Home-page: UNKNOWN
License: UNKNOWN
Download-URL: https://github.com/hhansen06/netbox-vpn-plugin/archive/refs/tags/0.8.2.tar.gz
Platform: UNKNOWN
